omnihash/__init__.py
omnihash/omnihash.py
omnihash-0.12.1.dist-info/DESCRIPTION.rst
omnihash-0.12.1.dist-info/METADATA
omnihash-0.12.1.dist-info/RECORD
omnihash-0.12.1.dist-info/WHEEL
omnihash-0.12.1.dist-info/entry_points.txt
omnihash-0.12.1.dist-info/metadata.json
omnihash-0.12.1.dist-info/top_level.txt
omnihash-0.12.1.dist-info/zip-safe
