Metadata-Version: 2.0
Name: omnihash
Version: 0.12.1
Summary: Hash files, strings, input streams and network resources in various common algorithms simultaneously
Home-page: https://github.com/Miserlou/omnihash
Author: Rich Jones
Author-email: rich@openwatch.net
License: MIT License
Platform: any
Classifier: Environment :: Console
Classifier: License :: OSI Approved :: Apache Software License
Classifier: Operating System :: OS Independent
Classifier: Programming Language :: Python
Classifier: Programming Language :: Python :: 2.7
Classifier: Programming Language :: Python :: 3.3
Classifier: Programming Language :: Python :: 3.4
Classifier: Programming Language :: Python :: 3.5
Classifier: Topic :: Internet :: WWW/HTTP
Classifier: Topic :: Internet :: WWW/HTTP :: Dynamic Content
Requires-Dist: click (==6.6)
Requires-Dist: colorama (==0.3.7)
Requires-Dist: crcmod (==1.7)
Requires-Dist: requests (>=2.10.0)
Requires-Dist: validators (==0.10.3)
Provides-Extra: pyblake2
Requires-Dist: pyblake2; extra == 'pyblake2'
Provides-Extra: sha3
Requires-Dist: sha3; extra == 'sha3'
